agentpy/__init__.py
agentpy/agent.py
agentpy/datadict.py
agentpy/examples.py
agentpy/experiment.py
agentpy/grid.py
agentpy/model.py
agentpy/network.py
agentpy/objects.py
agentpy/sample.py
agentpy/sequences.py
agentpy/space.py
agentpy/tools.py
agentpy/version.py
agentpy/visualization.py
tests/__init__.py
tests/test_datadict.py
tests/test_examples.py
tests/test_experiment.py
tests/test_grid.py
tests/test_init.py
tests/test_model.py
tests/test_network.py
tests/test_objects.py
tests/test_sample.py
tests/test_sequences.py
tests/test_space.py
tests/test_tools.py
tests/test_visualization.py
agentpy-0.1.5.dist-info/LICENSE
agentpy-0.1.5.dist-info/METADATA
agentpy-0.1.5.dist-info/WHEEL
agentpy-0.1.5.dist-info/top_level.txt
agentpy-0.1.5.dist-info/RECORD
