Metadata-Version: 2.1
Name: agentpy
Version: 0.1.5
Summary: Agent-based modeling in Python
Home-page: https://agentpy.readthedocs.io/
Author: Joël Foramitti
Author-email: joel.foramitti@uab.cat
License: BSD 3-Clause
Download-URL: https://github.com/JoelForamitti/agentpy
Platform: UNKNOWN
Classifier: Programming Language :: Python :: 3
Classifier: License :: OSI Approved :: BSD License
Classifier: Intended Audience :: Science/Research
Classifier: Operating System :: OS Independent
Requires-Python: >=3.6
Provides-Extra: docs
Provides-Extra: dev
